_bssclient_version.py
bssclient/__init__.py
bssclient/py.typed
bssclient/client/__init__.py
bssclient/client/bssclient.py
bssclient/client/config.py
bssclient/client/oauth.py
bssclient/models/__init__.py
bssclient/models/aufgabe.py
bssclient/models/ermittlungsauftrag.py
bssclient/models/events.py
bssclient/models/prozess.py
bssclient-0.3.0.dist-info/METADATA
bssclient-0.3.0.dist-info/WHEEL
bssclient-0.3.0.dist-info/licenses/LICENSE
bssclient-0.3.0.dist-info/RECORD
